Metadata-Version: 1.1
Name: seqpipe
Version: 0.0.7
Summary: Sequencing pipeline
Home-page: https://github.com/kpj/SeqPipe
Author: kpj
Author-email: kpjkpjkpjkpjkpjkpj@gmail.com
License: MIT
Keywords: bioinformatics sequencing pipeline alignment mapping
Platform: UNKNOWN
Classifier: Development Status :: 3 - Alpha
Classifier: Intended Audience :: Science/Research
Classifier: Topic :: Scientific/Engineering :: Bio-Informatics
Classifier: License :: OSI Approved :: MIT License
Classifier: Programming Language :: Python :: 3.6
